airflow_db_logger/__init__.py
airflow_db_logger/airflow_utils.py
airflow_db_logger/airlfow_config.py
airflow_db_logger/config.py
airflow_db_logger/data.py
airflow_db_logger/db.py
airflow_db_logger/exceptions.py
airflow_db_logger/handlers.py
airflow_db_logger/log.py
airflow_db_logger/logging_config.py
airflow_db_logger/operators.py
airflow_db_logger/shell_logging_config.py
airflow_db_logger/storage.py
airflow_db_logger/utils.py
airflow_db_logger-3.0.2.dist-info/METADATA
airflow_db_logger-3.0.2.dist-info/WHEEL
airflow_db_logger-3.0.2.dist-info/top_level.txt
airflow_db_logger-3.0.2.dist-info/RECORD
