Metadata-Version: 2.1
Name: airflow_db_logger
Version: 3.0.2
Summary: An airflow logger that stores its results in a database given an SQLAlchemy connection.
Home-page: https://github.com/LamaAni/AirflowDBLogger
Author: Zav Shotan
Author-email: 
License: docs/LICENSE
Platform: any
Requires-Python: >=3.6
